<annotation>
	<folder>新建文件夹 (6)</folder>
	<filename>000223.jpg</filename>
	<path>C:\Users\周菜\Desktop\新建文件夹 (6)\000223.jpg</path>
	<source>
		<database>Unknown</database>
	</source>
	<size>
		<width>600</width>
		<height>450</height>
		<depth>3</depth>
	</size>
	<segmented>0</segmented>
	<object>
		<name>hat</name>
		<pose>Unspecified</pose>
		<truncated>0</truncated>
		<difficult>0</difficult>
		<bndbox>
			<xmin>190</xmin>
			<ymin>191</ymin>
			<xmax>245</xmax>
			<ymax>240</ymax>
		</bndbox>
	</object>
	<object>
		<name>hat</name>
		<pose>Unspecified</pose>
		<truncated>0</truncated>
		<difficult>0</difficult>
		<bndbox>
			<xmin>292</xmin>
			<ymin>172</ymin>
			<xmax>351</xmax>
			<ymax>236</ymax>
		</bndbox>
	</object>
	<object>
		<name>hat</name>
		<pose>Unspecified</pose>
		<truncated>0</truncated>
		<difficult>0</difficult>
		<bndbox>
			<xmin>378</xmin>
			<ymin>125</ymin>
			<xmax>433</xmax>
			<ymax>190</ymax>
		</bndbox>
	</object>
</annotation>
