<annotation>
	<folder>新建文件夹 (6)</folder>
	<filename>000452.jpg</filename>
	<path>C:\Users\17804\Desktop\新建文件夹 (6)\000452.jpg</path>
	<source>
		<database>Unknown</database>
	</source>
	<size>
		<width>640</width>
		<height>420</height>
		<depth>3</depth>
	</size>
	<segmented>0</segmented>
	<object>
		<name>hat</name>
		<pose>Unspecified</pose>
		<truncated>1</truncated>
		<difficult>0</difficult>
		<bndbox>
			<xmin>288</xmin>
			<ymin>1</ymin>
			<xmax>401</xmax>
			<ymax>136</ymax>
		</bndbox>
	</object>
</annotation>
