<annotation>
	<folder>新建文件夹 (7)</folder>
	<filename>000487.jpg</filename>
	<path>C:\Users\hasee\Desktop\新建文件夹 (7)\000487.jpg</path>
	<source>
		<database>Unknown</database>
	</source>
	<size>
		<width>533</width>
		<height>355</height>
		<depth>3</depth>
	</size>
	<segmented>0</segmented>
	<object>
		<name>head</name>
		<pose>Unspecified</pose>
		<truncated>0</truncated>
		<difficult>0</difficult>
		<bndbox>
			<xmin>306</xmin>
			<ymin>83</ymin>
			<xmax>397</xmax>
			<ymax>174</ymax>
		</bndbox>
	</object>
	<object>
		<name>hat</name>
		<pose>Unspecified</pose>
		<truncated>0</truncated>
		<difficult>0</difficult>
		<bndbox>
			<xmin>196</xmin>
			<ymin>103</ymin>
			<xmax>273</xmax>
			<ymax>193</ymax>
		</bndbox>
	</object>
	<object>
		<name>hat</name>
		<pose>Unspecified</pose>
		<truncated>0</truncated>
		<difficult>0</difficult>
		<bndbox>
			<xmin>16</xmin>
			<ymin>47</ymin>
			<xmax>159</xmax>
			<ymax>171</ymax>
		</bndbox>
	</object>
	<object>
		<name>hat</name>
		<pose>Unspecified</pose>
		<truncated>0</truncated>
		<difficult>0</difficult>
		<bndbox>
			<xmin>391</xmin>
			<ymin>107</ymin>
			<xmax>451</xmax>
			<ymax>168</ymax>
		</bndbox>
	</object>
	<object>
		<name>hat</name>
		<pose>Unspecified</pose>
		<truncated>1</truncated>
		<difficult>0</difficult>
		<bndbox>
			<xmin>491</xmin>
			<ymin>102</ymin>
			<xmax>533</xmax>
			<ymax>157</ymax>
		</bndbox>
	</object>
</annotation>
