<annotation>
	<folder>新建文件夹 (7)</folder>
	<filename>000747.jpg</filename>
	<path>C:\Users\cxy18\Desktop\lableImage\data\新建文件夹 (7)\000747.jpg</path>
	<source>
		<database>Unknown</database>
	</source>
	<size>
		<width>420</width>
		<height>600</height>
		<depth>3</depth>
	</size>
	<segmented>0</segmented>
	<object>
		<name>hat</name>
		<pose>Unspecified</pose>
		<truncated>0</truncated>
		<difficult>0</difficult>
		<bndbox>
			<xmin>111</xmin>
			<ymin>199</ymin>
			<xmax>204</xmax>
			<ymax>283</ymax>
		</bndbox>
	</object>
</annotation>
